carquery/__init__.py
carquery/car_query.py
carquery-0.1.0.dist-info/LICENSE
carquery-0.1.0.dist-info/METADATA
carquery-0.1.0.dist-info/WHEEL
carquery-0.1.0.dist-info/top_level.txt
carquery-0.1.0.dist-info/RECORD
