Metadata-Version: 2.1
Name: carquery
Version: 0.1.0
Summary: A Python library for fetching car data from CarQueryAPI
Home-page: https://github.com/Salman0x01/Car-Model-Data-Scraper/tree/main
Author: Salman Khan
Author-email: salman@sprotechs.com
Classifier: Programming Language :: Python :: 3
Classifier: License :: OSI Approved :: MIT License
Classifier: Operating System :: OS Independent
Requires-Python: >=3.6
License-File: LICENSE
Requires-Dist: requests
Requires-Dist: prettytable
Requires-Dist: tqdm
